[
{
"name":"Batman #131",
"img":"https://s3.amazonaws.com/comicgeeks/comics/covers/large-2331867.jpg?1672375345",
"date":"20230108"
},
{
"name":"Fantastic Four #3",
"img":"https://s3.amazonaws.com/comicgeeks/comics/covers/large-3081250.jpg?1672528539",
"date":"20230108"
},
{
"name":"Scarlet Witch #1",
"img":"https://s3.amazonaws.com/comicgeeks/comics/covers/large-4776185.jpg?1672530905",
"date":"20230108"
},
{
"name":"Dark Knights of Steel #9",
"img":"https://s3.amazonaws.com/comicgeeks/comics/covers/large-3690310.jpg?1669320266",
"date":"20230108"
},
{
"name":"",
"img":"",
"date":"20230115"
},
{
"name":"",
"img":"",
"date":"20230115"
},
{
"name":"",
"img":"",
"date":"20230115"
},
{
"name":"",
"img":"",
"date":"20230115"
},
{
"name":"",
"img":"",
"date":""
}
]
